MANIFEST.in
README.rst
execute_cmd.py
setup.py
executecmd.egg-info/PKG-INFO
executecmd.egg-info/SOURCES.txt
executecmd.egg-info/dependency_links.txt
executecmd.egg-info/entry_points.txt
executecmd.egg-info/requires.txt
executecmd.egg-info/top_level.txt
executecmd.egg-info/zip-safe