Metadata-Version: 1.1
Name: executecmd
Version: 1.0.10
Summary: execute remote command. 
Home-page: https://www.github.com/ShichaoMa/exec_cmd
Author: cn
Author-email: cnaafhvk@foxmail.com
License: MIT
Keywords: execute command
Platform: UNKNOWN
Classifier: License :: OSI Approved :: MIT License
Classifier: Programming Language :: Python
Classifier: Intended Audience :: Developers
Classifier: Operating System :: OS Independent
